yandex_delivery/__init__.py
yandex_delivery/base_methods.py
yandex_delivery/delivery_api.py
yandex_delivery/exceptions.py
yandex_delivery/rest_adapter.py
yandex_delivery/rest_result.py
yandex_delivery_api-1.0.2.1.dist-info/LICENSE
yandex_delivery_api-1.0.2.1.dist-info/METADATA
yandex_delivery_api-1.0.2.1.dist-info/WHEEL
yandex_delivery_api-1.0.2.1.dist-info/top_level.txt
yandex_delivery_api-1.0.2.1.dist-info/RECORD
