Metadata-Version: 2.1
Name: yandex-delivery-api
Version: 1.0.2.1
Summary: Python wrapper for Yandex Delivery API
Author-email: edm.rud3nko@yandex.ru
License-File: LICENSE
